faultybot/__init__.py
faultybot/function.py
faultybot-0.0.2.dist-info/LICENSE
faultybot-0.0.2.dist-info/METADATA
faultybot-0.0.2.dist-info/WHEEL
faultybot-0.0.2.dist-info/top_level.txt
faultybot-0.0.2.dist-info/RECORD
