Metadata-Version: 2.1
Name: faultybot
Version: 0.0.2
Summary: Faultybot Discord Handler
Home-page: https://github.com/jplight/faultybot
License: MIT
Keywords: Python Discord Faultybot
Platform: UNKNOWN
Classifier: Development Status :: 1 - Planning
Classifier: Intended Audience :: Developers
Classifier: Intended Audience :: Science/Research
Classifier: License :: OSI Approved :: MIT License
Classifier: Operating System :: OS Independent
Classifier: Programming Language :: Python
Classifier: Programming Language :: Python :: 3.8
Classifier: Programming Language :: Python :: 3.9
Requires-Python: >=3.8.*
Requires-Dist: aiohttp (>=3.7.4.post0)
Requires-Dist: async-lichess-sdk (>=1.1.0.7)
Requires-Dist: async-timeout (>=3.0.1)
Requires-Dist: attrs (>=20.3.0)
Requires-Dist: certifi (>=2020.12.5)
Requires-Dist: chardet (>=4.0.0)
Requires-Dist: chess (>=1.5.0)
Requires-Dist: discord (>=1.0.1)
Requires-Dist: discord.py (>=1.7.2)
Requires-Dist: idna (>=2.10)
Requires-Dist: multidict (>=5.1.0)
Requires-Dist: python-chess (>=1.999)
Requires-Dist: python-lichess (>=0.9)
Requires-Dist: requests (>=2.25.1)
Requires-Dist: six (>=1.15.0)
Requires-Dist: typing-extensions (>=3.10.0.0)
Requires-Dist: urllib3 (>=1.26.4)
Requires-Dist: uuid (>=1.30)
Requires-Dist: yarl (>=1.6.3)
Requires-Dist: virtualenv (>=20.4.6)
